litex.cxpool-1.1.1-py3.7-nspkg.pth
litex/cxpool/__init__.py
litex.cxpool-1.1.1.dist-info/METADATA
litex.cxpool-1.1.1.dist-info/WHEEL
litex.cxpool-1.1.1.dist-info/namespace_packages.txt
litex.cxpool-1.1.1.dist-info/top_level.txt
litex.cxpool-1.1.1.dist-info/RECORD
