Metadata-Version: 2.1
Name: litex.cxpool
Version: 1.1.1
Summary: Native Oracle Session Pool implementation for SQLAlchemy
Home-page: UNKNOWN
Author: Michal Wegrzynek
Author-email: mwegrzynek@litexservice.pl
License: BSD like, see http://repoze.org/license.html
Keywords: cxpool oracle sessionpool sqlalchemy proxy
Platform: UNKNOWN
Classifier: Programming Language :: Python
Classifier: Topic :: Database :: Front-Ends
Requires-Dist: setuptools
Requires-Dist: cx-Oracle
Requires-Dist: sqlalchemy
